Workbook

Sheet Hoja1
A1: Módulo del formulario de aplicación | B1: Código del formulario de aplicación | C1: Número del formulario de aplicación | D1: Código de cliente | E1: Razón Social | F1: Vendedor | G1: Código de imputación | H1: Código de subcuenta | I1: Fecha de Movimiento | J1: Saldo Nacional | K1: Acumulado Nacional | L1: Sucursal | M1: Numero completo factura (suc+num)
A2: VT | B2: ANTMI | C2: 4881 | D2: I/167 | E2: =VLOOKUP(D:D,Hoja2!A:B,2,FALSE) -> ANGLADA ALFONSO | F2: V1 | G2: CC | H2: I/167 | I2: 2/2/2018 | J2: -2.5 | K2: -2.5 | M2: -00004881
A3: VT | B3: NDB17 | C3: 15 | D3: I/167 | E3: =VLOOKUP(D:D,Hoja2!A:B,2,FALSE) -> ANGLADA ALFONSO | F3: V1 | G3: CC | H3: I/167 | I3: 21/9/2019 | J3: 2.5 | K3: 0 | L3: 0017 | M3: 0017-00000015
A4: VT | B4: FA17 | C4: 3790 | D4: I/169 | E4: =VLOOKUP(D:D,Hoja2!A:B,2,FALSE) -> ARDAPEZ SA | F4: JOGR | G4: CC | H4: I/169 | I4: 18/1/2023 | J4: 1734000 | K4: 1734000 | L4: 0017 | M4: 0017-00003790
A5: VT | B5: NCA17 | C5: 168 | D5: I/169 | E5: =VLOOKUP(D:D,Hoja2!A:B,2,FALSE) -> ARDAPEZ SA | F5: JOGR | G5: CC | H5: I/169 | I5: 18/1/2023 | J5: -1734000 | K5: 0 | L5: 0017 | M5: 0017-00000168
A6: VT | B6: FA17 | C6: 7224 | D6: I/227 | E6: =VLOOKUP(D:D,Hoja2!A:B,2,FALSE) -> MARDI SA | F6: JOGR | G6: CC | H6: I/227 | I6: 22/4/2026 | J6: 19324800 | K6: 19324800 | L6: 0017 | M6: 0017-00007224
A7: VT | B7: FA17 | C7: 7240 | D7: I/227 | E7: =VLOOKUP(D:D,Hoja2!A:B,2,FALSE) -> MARDI SA | F7: JOGR | G7: CC | H7: I/227 | I7: 29/4/2026 | J7: 23015300 | K7: 42340100 | L7: 0017 | M7: 0017-00007240
A8: VT | B8: FA17 | C8: 7257 | D8: I/227 | E8: =VLOOKUP(D:D,Hoja2!A:B,2,FALSE) -> MARDI SA | F8: JOGR | G8: CC | H8: I/227 | I8: 4/5/2026 | J8: 20431950 | K8: 62772050 | L8: 0017 | M8: 0017-00007257
A9: VT | B9: FA17 | C9: 7284 | D9: I/227 | E9: =VLOOKUP(D:D,Hoja2!A:B,2,FALSE) -> MARDI SA | F9: JOGR | G9: CC | H9: I/227 | I9: 6/5/2026 | J9: 24827000 | K9: 87599050 | L9: 0017 | M9: 0017-00007284
A10: VT | B10: FA17 | C10: 7302 | D10: I/227 | E10: =VLOOKUP(D:D,Hoja2!A:B,2,FALSE) -> MARDI SA | F10: JOGR | G10: CC | H10: I/227 | I10: 8/5/2026 | J10: 28819450 | K10: 116418500 | L10: 0017 | M10: 0017-00007302
A11: VT | B11: NCA17 | C11: 91 | D11: I/241 | E11: =VLOOKUP(D:D,Hoja2!A:B,2,FALSE) -> GIORNO SA | F11: JOMO | G11: CC | H11: I/241 | I11: 1/7/2020 | J11: -0.01 | K11: -0.01 | L11: 0017 | M11: 0017-00000091
A12: VT | B12: FA17 | C12: 2189 | D12: I/241 | E12: =VLOOKUP(D:D,Hoja2!A:B,2,FALSE) -> GIORNO SA | F12: JOMO | G12: CC | H12: I/241 | I12: 28/8/2020 | J12: 1274713.2 | K12: 1274713.2 | L12: 0017 | M12: 0017-00002189
A13: VT | B13: FA17 | C13: 2191 | D13: I/241 | E13: =VLOOKUP(D:D,Hoja2!A:B,2,FALSE) -> GIORNO SA | F13: JOMO | G13: CC | H13: I/241 | I13: 31/8/2020 | J13: 2574624.3 | K13: 3849337.5 | L13: 0017 | M13: 0017-00002191
A14: VT | B14: NCA17 | C14: 99 | D14: I/241 | E14: =VLOOKUP(D:D,Hoja2!A:B,2,FALSE) -> GIORNO SA | F14: JOMO | G14: CC | H14: I/241 | I14: 31/8/2020 | J14: -1316317.5 | K14: 2533020 | L14: 0017 | M14: 0017-00000099
... A23: VT | B23: FA17 | C23: 7303 | D23: I/443 | E23: =VLOOKUP(D:D,Hoja2!A:B,2,FALSE) -> NATUSUR SA | F23: JOGR | G23: CC | H23: I/443 | I23: 8/5/2026 | J23: 31118945 | K23: 75097680 | L23: 0017 | M23: 0017-00007303
A24: VT | B24: FAINI | C24: 783 | D24: I/444 | E24: =VLOOKUP(D:D,Hoja2!A:B,2,FALSE) -> AGUSTINER SA | G24: CCE | H24: I/444 | I24: 13/10/2016 | J24: 280180.58 | K24: 280180.58 | L24: 0018 | M24: 0018-00000783
A25: VT | B25: FAINI | C25: 839 | D25: I/444 | E25: =VLOOKUP(D:D,Hoja2!A:B,2,FALSE) -> AGUSTINER SA | G25: CCE | H25: I/444 | I25: 16/11/2016 | J25: 288058.22 | K25: 568238.8 | L25: 0018 | M25: 0018-00000839
A26: VT | B26: FAINI | C26: 847 | D26: I/444 | E26: =VLOOKUP(D:D,Hoja2!A:B,2,FALSE) -> AGUSTINER SA | G26: CCE | H26: I/444 | I26: 6/12/2016 | J26: 287907.42 | K26: 856146.22 | L26: 0018 | M26: 0018-00000847
A27: VT | B27: FAINI | C27: 848 | D27: I/444 | E27: =VLOOKUP(D:D,Hoja2!A:B,2,FALSE) -> AGUSTINER SA | G27: CCE | H27: I/444 | I27: 14/12/2016 | J27: 57987.09 | K27: 914133.31 | L27: 0018 | M27: 0018-00000848
A28: VT | B28: FAINI | C28: 10000632 | D28: I/448 | E28: =VLOOKUP(D:D,Hoja2!A:B,2,FALSE) -> ARHEHPEZ SA | G28: CC | H28: I/448 | I28: 23/1/2014 | J28: 121 | K28: 121 | L28: 0018 | M28: 0018-10000632
A29: VT | B29: FAINI | C29: 10000636 | D29: I/448 | E29: =VLOOKUP(D:D,Hoja2!A:B,2,FALSE) -> ARHEHPEZ SA | G29: CC | H29: I/448 | I29: 27/1/2014 | J29: 12584 | K29: 12705 | L29: 0018 | M29: 0018-10000636
A30: VT | B30: FA17 | C30: 208 | D30: I/468 | E30: =VLOOKUP(D:D,Hoja2!A:B,2,FALSE) -> FRIGOSUR SRL | F30: V1 | G30: CC | H30: I/468 | I30: 29/8/2017 | J30: 125090.63 | K30: 125090.63 | L30: 0017 | M30: 0017-00000208
A31: VT | B31: FA17 | C31: 223 | D31: I/468 | E31: =VLOOKUP(D:D,Hoja2!A:B,2,FALSE) -> FRIGOSUR SRL | F31: V1 | G31: CC | H31: I/468 | I31: 29/8/2017 | J31: 126985.94 | K31: 252076.57 | L31: 0017 | M31: 0017-00000223
A32: VT | B32: FA17 | C32: 208 | D32: I/468 | E32: =VLOOKUP(D:D,Hoja2!A:B,2,FALSE) -> FRIGOSUR SRL | F32: V1 | G32: CCE | H32: I/468 | I32: 6/9/2017 | J32: -125090.63 | K32: 126985.94 | L32: 0017 | M32: 0017-00000208
A33: VT | B33: FA17 | C33: 223 | D33: I/468 | E33: =VLOOKUP(D:D,Hoja2!A:B,2,FALSE) -> FRIGOSUR SRL | F33: V1 | G33: CCE | H33: I/468 | I33: 6/9/2017 | J33: -126985.94 | K33: 0 | L33: 0017 | M33: 0017-00000223
A34: VT | B34: FA17 | C34: 7276 | D34: I/468 | E34: =VLOOKUP(D:D,Hoja2!A:B,2,FALSE) -> FRIGOSUR SRL | F34: V1 | G34: CC | H34: I/468 | I34: 6/5/2026 | J34: 24928750 | K34: 24928750 | L34: 0017 | M34: 0017-00007276
A35: VT | B35: FA17 | C35: 7295 | D35: I/468 | E35: =VLOOKUP(D:D,Hoja2!A:B,2,FALSE) -> FRIGOSUR SRL | F35: V1 | G35: CC | H35: I/468 | I35: 8/5/2026 | J35: 28634375 | K35: 53563125 | L35: 0017 | M35: 0017-00007295
A36: VT | B36: FAINI | C36: 100000001 | D36: I/509 | E36: =VLOOKUP(D:D,Hoja2!A:B,2,FALSE) -> O. Y J. DI MARCO | G36: CC | H36: I/509 | I36: 1/1/2001 | J36: 13522.44 | K36: 13522.44 | L36: 0018 | M36: 0018-00000001
A37: VT | B37: NCA18 | C37: 49 | D37: I/509 | E37: =VLOOKUP(D:D,Hoja2!A:B,2,FALSE) -> O. Y J. DI MARCO | G37: CC | H37: I/509 | I37: 30/5/2022 | J37: -13522.44 | K37: 0 | L37: 0018 | M37: 0018-00000049
A38: VT | B38: FA17 | C38: 2118 | D38: I/58 | E38: =VLOOKUP(D:D,Hoja2!A:B,2,FALSE) -> ANTONIO MIRALLES SA | F38: SEGU | G38: CC | H38: I/58 | I38: 28/7/2020 | J38: 5531256.7 | K38: 5531256.7 | L38: 0017 | M38: 0017-00002118
A39: VT | B39: NCA17 | C39: 96 | D39: I/58 | E39: =VLOOKUP(D:D,Hoja2!A:B,2,FALSE) -> ANTONIO MIRALLES SA | F39: SEGU | G39: CC | H39: I/58 | I39: 30/7/2020 | J39: -5531256.7 | K39: -0.0099999998 | L39: 0017 | M39: 0017-00000096
A40: VT | B40: AJUIN+ | C40: 28 | D40: I/58 | E40: =VLOOKUP(D:D,Hoja2!A:B,2,FALSE) -> ANTONIO MIRALLES SA | F40: SEGU | G40: CCE | H40: I/58 | I40: 6/11/2024 | J40: 0.01 | K40: 2.2351742e-10 | L40: 0013 | M40: 0013-00000028
A41: VT | B41: FAINI | C41: 1065 | D41: I/596 | E41: =VLOOKUP(D:D,Hoja2!A:B,2,FALSE) -> 27 DE NOVIEMBRE SA | F41: JOGR | G41: CCE | H41: I/596 | I41: 12/5/2017 | J41: 0.01 | K41: 0.01 | L41: 0018 | M41: 0018-00001065
A42: VT | B42: FAINI | C42: 1079 | D42: I/596 | E42: =VLOOKUP(D:D,Hoja2!A:B,2,FALSE) -> 27 DE NOVIEMBRE SA | F42: JOGR | G42: CCE | H42: I/596 | I42: 23/5/2017 | J42: -0.01 | K42: 0 | L42: 0018 | M42: 0018-00001079
A43: VT | B43: FA17 | C43: 204 | D43: I/596 | E43: =VLOOKUP(D:D,Hoja2!A:B,2,FALSE) -> 27 DE NOVIEMBRE SA | F43: JOGR | G43: CC | H43: I/596 | I43: 29/8/2017 | J43: 111104 | K43: 111104 | L43: 0017 | M43: 0017-00000204
A44: VT | B44: FA17 | C44: 204 | D44: I/596 | E44: =VLOOKUP(D:D,Hoja2!A:B,2,FALSE) -> 27 DE NOVIEMBRE SA | F44: JOGR | G44: CCE | H44: I/596 | I44: 4/9/2017 | J44: -111104 | K44: 0 | L44: 0017 | M44: 0017-00000204
A45: VT | B45: FA17 | C45: 798 | D45: I/596 | E45: =VLOOKUP(D:D,Hoja2!A:B,2,FALSE) -> 27 DE NOVIEMBRE SA | F45: JOGR | G45: CC | H45: I/596 | I45: 17/9/2018 | J45: 230384 | K45: 230384 | L45: 0017 | M45: 0017-00000798
A46: VT | B46: NCA17 | C46: 40 | D46: I/596 | E46: =VLOOKUP(D:D,Hoja2!A:B,2,FALSE) -> 27 DE NOVIEMBRE SA | F46: JOGR | G46: CC | H46: I/596 | I46: 20/9/2018 | J46: -230384 | K46: 0 | L46: 0017 | M46: 0017-00000040
A47: VT | B47: ANTMI | C47: 6713 | D47: I/596 | E47: =VLOOKUP(D:D,Hoja2!A:B,2,FALSE) -> 27 DE NOVIEMBRE SA | F47: JOGR | G47: CC | H47: I/596 | I47: 1/2/2022 | J47: -15541.35 | K47: -15541.35 | M47: -00006713
A48: VT | B48: FA17 | C48: 3052 | D48: I/596 | E48: =VLOOKUP(D:D,Hoja2!A:B,2,FALSE) -> 27 DE NOVIEMBRE SA | F48: JOGR | G48: CC | H48: I/596 | I48: 10/2/2022 | J48: 15541.35 | K48: 0 | L48: 0017 | M48: 0017-00003052
A49: VT | B49: ANTMI | C49: 9591 | D49: I/596 | E49: =VLOOKUP(D:D,Hoja2!A:B,2,FALSE) -> 27 DE NOVIEMBRE SA | F49: JOGR | G49: CC | H49: I/596 | I49: 21/4/2026 | J49: -450056.42 | K49: -450056.42 | M49: -00009591
A50: VT | B50: FA17 | C50: 7227 | D50: I/596 | E50: =VLOOKUP(D:D,Hoja2!A:B,2,FALSE) -> 27 DE NOVIEMBRE SA | F50: JOGR | G50: CC | H50: I/596 | I50: 29/4/2026 | J50: 19568588 | K50: 19118531 | L50: 0017 | M50: 0017-00007227
A51: VT | B51: FA17 | C51: 7246 | D51: I/596 | E51: =VLOOKUP(D:D,Hoja2!A:B,2,FALSE) -> 27 DE NOVIEMBRE SA | F51: JOGR | G51: CC | H51: I/596 | I51: 4/5/2026 | J51: 14146988 | K51: 33265519 | L51: 0017 | M51: 0017-00007246
A52: VT | B52: FA17 | C52: 7271 | D52: I/596 | E52: =VLOOKUP(D:D,Hoja2!A:B,2,FALSE) -> 27 DE NOVIEMBRE SA | F52: JOGR | G52: CC | H52: I/596 | I52: 6/5/2026 | J52: 10447875 | K52: 43713394 | L52: 0017 | M52: 0017-00007271
A53: VT | B53: FA17 | C53: 7291 | D53: I/596 | E53: =VLOOKUP(D:D,Hoja2!A:B,2,FALSE) -> 27 DE NOVIEMBRE SA | F53: JOGR | G53: CC | H53: I/596 | I53: 8/5/2026 | J53: 14231700 | K53: 57945094 | L53: 0017 | M53: 0017-00007291
A54: VT | B54: FA17 | C54: 7307 | D54: I/596 | E54: =VLOOKUP(D:D,Hoja2!A:B,2,FALSE) -> 27 DE NOVIEMBRE SA | F54: JOGR | G54: CC | H54: I/596 | I54: 13/5/2026 | J54: 10024312 | K54: 67969406 | L54: 0017 | M54: 0017-00007307
A55: VT | B55: FA17 | C55: 210 | D55: I/6 | E55: =VLOOKUP(D:D,Hoja2!A:B,2,FALSE) -> MARISQUERIA SANTA RITA SRL | F55: JOGR | G55: CC | H55: I/6 | I55: 29/8/2017 | J55: 145507.25 | K55: 145507.25 | L55: 0017 | M55: 0017-00000210
A56: VT | B56: FA17 | C56: 229 | D56: I/6 | E56: =VLOOKUP(D:D,Hoja2!A:B,2,FALSE) -> MARISQUERIA SANTA RITA SRL | F56: JOGR | G56: CC | H56: I/6 | I56: 29/8/2017 | J56: 83395.2 | K56: 228902.45 | L56: 0017 | M56: 0017-00000229
A57: VT | B57: FA17 | C57: 210 | D57: I/6 | E57: =VLOOKUP(D:D,Hoja2!A:B,2,FALSE) -> MARISQUERIA SANTA RITA SRL | F57: JOGR | G57: CCE | H57: I/6 | I57: 5/9/2017 | J57: -145507.25 | K57: 83395.2 | L57: 0017 | M57: 0017-00000210
A58: VT | B58: FA17 | C58: 229 | D58: I/6 | E58: =VLOOKUP(D:D,Hoja2!A:B,2,FALSE) -> MARISQUERIA SANTA RITA SRL | F58: JOGR | G58: CCE | H58: I/6 | I58: 5/9/2017 | J58: -83395.2 | K58: 1.4551915e-11 | L58: 0017 | M58: 0017-00000229
A59: VT | B59: FA17 | C59: 289 | D59: I/6 | E59: =VLOOKUP(D:D,Hoja2!A:B,2,FALSE) -> MARISQUERIA SANTA RITA SRL | F59: JOGR | G59: CC | H59: I/6 | I59: 2/10/2017 | J59: 143745.03 | K59: 143745.03 | L59: 0017 | M59: 0017-00000289
A60: VT | B60: NCA17 | C60: 20 | D60: I/6 | E60: =VLOOKUP(D:D,Hoja2!A:B,2,FALSE) -> MARISQUERIA SANTA RITA SRL | F60: JOGR | G60: CC | H60: I/6 | I60: 2/10/2017 | J60: -143745.03 | K60: 2.910383e-11 | L60: 0017 | M60: 0017-00000020
A61: VT | B61: FA17 | C61: 4154 | D61: I/6 | E61: =VLOOKUP(D:D,Hoja2!A:B,2,FALSE) -> MARISQUERIA SANTA RITA SRL | F61: JOGR | G61: CC | H61: I/6 | I61: 30/5/2023 | J61: 2095500 | K61: 2095500 | L61: 0017 | M61: 0017-00004154
... A67: VT | B67: NCA17 | C67: 203 | D67: I/6 | E67: =VLOOKUP(D:D,Hoja2!A:B,2,FALSE) -> MARISQUERIA SANTA RITA SRL | F67: JOGR | G67: CC | H67: I/6 | I67: 11/8/2023 | J67: -200000 | K67: 0 | L67: 0017 | M67: 0017-00000203
A68: VT | B68: ANTMI | C68: 8682 | D68: I/6 | E68: =VLOOKUP(D:D,Hoja2!A:B,2,FALSE) -> MARISQUERIA SANTA RITA SRL | F68: JOGR | G68: CC | H68: I/6 | I68: 20/11/2024 | J68: -10000 | K68: -10000 | M68: -00008682
A69: VT | B69: FA17 | C69: 2 | D69: I/636 | E69: =VLOOKUP(D:D,Hoja2!A:B,2,FALSE) -> PROYECTOS DEL MAR SRL | F69: V1 | G69: CC | H69: I/636 | I69: 2/6/2017 | J69: 91476 | K69: 91476 | L69: 0017 | M69: 0017-00000002
A70: VT | B70: FA17 | C70: 3 | D70: I/636 | E70: =VLOOKUP(D:D,Hoja2!A:B,2,FALSE) -> PROYECTOS DEL MAR SRL | F70: V1 | G70: CC | H70: I/636 | I70: 5/6/2017 | J70: 91476 | K70: 182952 | L70: 0017 | M70: 0017-00000003
A71: VT | B71: NCA17 | C71: 2 | D71: I/636 | E71: =VLOOKUP(D:D,Hoja2!A:B,2,FALSE) -> PROYECTOS DEL MAR SRL | F71: V1 | G71: CC | H71: I/636 | I71: 5/6/2017 | J71: -182952 | K71: 0 | L71: 0017 | M71: 0017-00000002
A72: VT | B72: FA17 | C72: 30 | D72: I/636 | E72: =VLOOKUP(D:D,Hoja2!A:B,2,FALSE) -> PROYECTOS DEL MAR SRL | F72: V1 | G72: CC | H72: I/636 | I72: 23/6/2017 | J72: 90098.4 | K72: 90098.4 | L72: 0017 | M72: 0017-00000030
A73: VT | B73: NCA17 | C73: 5 | D73: I/636 | E73: =VLOOKUP(D:D,Hoja2!A:B,2,FALSE) -> PROYECTOS DEL MAR SRL | F73: V1 | G73: CC | H73: I/636 | I73: 23/6/2017 | J73: -90098.4 | K73: 0 | L73: 0017 | M73: 0017-00000005
A74: VT | B74: FA17 | C74: 1711 | D74: I/636 | E74: =VLOOKUP(D:D,Hoja2!A:B,2,FALSE) -> PROYECTOS DEL MAR SRL | F74: V1 | G74: CC | H74: I/636 | I74: 10/12/2019 | J74: 181044.5 | K74: 181044.5 | L74: 0017 | M74: 0017-00001711
A75: VT | B75: NCA17 | C75: 76 | D75: I/636 | E75: =VLOOKUP(D:D,Hoja2!A:B,2,FALSE) -> PROYECTOS DEL MAR SRL | F75: V1 | G75: CC | H75: I/636 | I75: 12/12/2019 | J75: -181044.5 | K75: 0 | L75: 0017 | M75: 0017-00000076
A76: VT | B76: FA17 | C76: 6402 | D76: I/636 | E76: =VLOOKUP(D:D,Hoja2!A:B,2,FALSE) -> PROYECTOS DEL MAR SRL | F76: V1 | G76: CC | H76: I/636 | I76: 24/7/2025 | J76: 16730438 | K76: 16730438 | L76: 0017 | M76: 0017-00006402
A77: VT | B77: NCA17 | C77: 246 | D77: I/636 | E77: =VLOOKUP(D:D,Hoja2!A:B,2,FALSE) -> PROYECTOS DEL MAR SRL | F77: V1 | G77: CC | H77: I/636 | I77: 25/7/2025 | J77: -16730438 | K77: 0 | L77: 0017 | M77: 0017-00000246
A78: VT | B78: FA17 | C78: 7304 | D78: I/636 | E78: =VLOOKUP(D:D,Hoja2!A:B,2,FALSE) -> PROYECTOS DEL MAR SRL | F78: V1 | G78: CC | H78: I/636 | I78: 8/5/2026 | J78: 11812625 | K78: 11812625 | L78: 0017 | M78: 0017-00007304
A79: VT | B79: NCA17 | C79: 148 | D79: I/69 | E79: =VLOOKUP(D:D,Hoja2!A:B,2,FALSE) -> MARBELLA SAIYC | F79: SEGU | G79: CC | H79: I/69 | I79: 10/3/2022 | J79: -13189 | K79: -13189 | L79: 0017 | M79: 0017-00000148
A80: VT | B80: ANTMI | C80: 6906 | D80: I/69 | E80: =VLOOKUP(D:D,Hoja2!A:B,2,FALSE) -> MARBELLA SAIYC | F80: SEGU | G80: CC | H80: I/69 | I80: 18/7/2022 | J80: -37752 | K80: -50941 | M80: -00006906
A81: VT | B81: FA17 | C81: 3315 | D81: I/69 | E81: =VLOOKUP(D:D,Hoja2!A:B,2,FALSE) -> MARBELLA SAIYC | F81: SEGU | G81: CC | H81: I/69 | I81: 21/7/2022 | J81: 50941 | K81: 0 | L81: 0017 | M81: 0017-00003315
A82: VT | B82: FAINI | C82: 10000621 | D82: I/7063 | E82: =VLOOKUP(D:D,Hoja2!A:B,2,FALSE) -> LAKSUR SA | G82: CC | H82: I/7063 | I82: 17/10/2013 | J82: 2949.75 | K82: 2949.75 | L82: 0018 | M82: 0018-10000621
A83: VT | B83: FAINI | C83: 10000622 | D83: I/7063 | E83: =VLOOKUP(D:D,Hoja2!A:B,2,FALSE) -> LAKSUR SA | G83: CC | H83: I/7063 | I83: 17/10/2013 | J83: 18.15 | K83: 2967.9 | L83: 0018 | M83: 0018-10000622
A84: VT | B84: FAINI | C84: 10000623 | D84: I/7063 | E84: =VLOOKUP(D:D,Hoja2!A:B,2,FALSE) -> LAKSUR SA | G84: CC | H84: I/7063 | I84: 6/11/2013 | J84: 15000 | K84: 17967.9 | L84: 0018 | M84: 0018-10000623
A85: VT | B85: FAINI | C85: 10000624 | D85: I/7063 | E85: =VLOOKUP(D:D,Hoja2!A:B,2,FALSE) -> LAKSUR SA | G85: CC | H85: I/7063 | I85: 6/11/2013 | J85: 121.3 | K85: 18089.2 | L85: 0018 | M85: 0018-10000624
A86: VT | B86: FAINI | C86: 10000625 | D86: I/7063 | E86: =VLOOKUP(D:D,Hoja2!A:B,2,FALSE) -> LAKSUR SA | G86: CC | H86: I/7063 | I86: 27/11/2013 | J86: 45000 | K86: 63089.2 | L86: 0018 | M86: 0018-10000625
A87: VT | B87: FAINI | C87: 10000626 | D87: I/7063 | E87: =VLOOKUP(D:D,Hoja2!A:B,2,FALSE) -> LAKSUR SA | G87: CC | H87: I/7063 | I87: 27/11/2013 | J87: 372.9 | K87: 63462.1 | L87: 0018 | M87: 0018-10000626
A88: VT | B88: FAINI | C88: 100049769 | D88: I/7107 | E88: =VLOOKUP(D:D,Hoja2!A:B,2,FALSE) -> FLESHMAR SRL(EN FORMACION) | G88: CCE | H88: I/7107 | I88: 17/1/2011 | J88: 19405.62 | K88: 19405.62 | L88: 0018 | M88: 0018-00049769
A89: VT | B89: FAINI | C89: 10049781 | D89: I/7107 | E89: =VLOOKUP(D:D,Hoja2!A:B,2,FALSE) -> FLESHMAR SRL(EN FORMACION) | G89: CC | H89: I/7107 | I89: 24/1/2011 | J89: 17998.85 | K89: 37404.47 | L89: 0018 | M89: 0018-10049781
A90: VT | B90: FAINI | C90: 10000383 | D90: I/7107 | E90: =VLOOKUP(D:D,Hoja2!A:B,2,FALSE) -> FLESHMAR SRL(EN FORMACION) | G90: CC | H90: I/7107 | I90: 6/5/2011 | J90: 7000 | K90: 44404.47 | L90: 0018 | M90: 0018-10000383
A91: VT | B91: FAINI | C91: 10000384 | D91: I/7107 | E91: =VLOOKUP(D:D,Hoja2!A:B,2,FALSE) -> FLESHMAR SRL(EN FORMACION) | G91: CC | H91: I/7107 | I91: 6/5/2011 | J91: 60.5 | K91: 44464.97 | L91: 0018 | M91: 0018-10000384
A92: VT | B92: FAINI | C92: 10000394 | D92: I/7107 | E92: =VLOOKUP(D:D,Hoja2!A:B,2,FALSE) -> FLESHMAR SRL(EN FORMACION) | G92: CC | H92: I/7107 | I92: 23/5/2011 | J92: 7000 | K92: 51464.97 | L92: 0018 | M92: 0018-10000394
A93: VT | B93: FAINI | C93: 10000395 | D93: I/7107 | E93: =VLOOKUP(D:D,Hoja2!A:B,2,FALSE) -> FLESHMAR SRL(EN FORMACION) | G93: CC | H93: I/7107 | I93: 23/5/2011 | J93: 60.5 | K93: 51525.47 | L93: 0018 | M93: 0018-10000395
A94: VT | B94: NCA18 | C94: 58 | D94: I/7107 | E94: =VLOOKUP(D:D,Hoja2!A:B,2,FALSE) -> FLESHMAR SRL(EN FORMACION) | G94: CC | H94: I/7107 | I94: 31/5/2022 | J94: -51525.47 | K94: 0 | L94: 0018 | M94: 0018-00000058
A95: VT | B95: ANTMI | C95: 9116 | D95: I/7116 | E95: =VLOOKUP(D:D,Hoja2!A:B,2,FALSE) -> LACAR FISH SA | F95: JOGR | G95: CC | H95: I/7116 | I95: 22/7/2025 | J95: -100 | K95: -100 | M95: -00009116
A96: VT | B96: FA17 | C96: 7253 | D96: I/7116 | E96: =VLOOKUP(D:D,Hoja2!A:B,2,FALSE) -> LACAR FISH SA | F96: JOGR | G96: CC | H96: I/7116 | I96: 4/5/2026 | J96: 11318175 | K96: 11318075 | L96: 0017 | M96: 0017-00007253
A97: VT | B97: FA17 | C97: 7279 | D97: I/7116 | E97: =VLOOKUP(D:D,Hoja2!A:B,2,FALSE) -> LACAR FISH SA | F97: JOGR | G97: CC | H97: I/7116 | I97: 6/5/2026 | J97: 14780205 | K97: 26098280 | L97: 0017 | M97: 0017-00007279
A98: VT | B98: FA17 | C98: 7298 | D98: I/7116 | E98: =VLOOKUP(D:D,Hoja2!A:B,2,FALSE) -> LACAR FISH SA | F98: JOGR | G98: CC | H98: I/7116 | I98: 8/5/2026 | J98: 14380740 | K98: 40479020 | L98: 0017 | M98: 0017-00007298
A99: VT | B99: FAINI | C99: 10049728 | D99: I/7128 | E99: =VLOOKUP(D:D,Hoja2!A:B,2,FALSE) -> LINEAERRE SA | G99: CC | H99: I/7128 | I99: 21/12/2010 | J99: 399.3 | K99: 399.3 | L99: 0018 | M99: 0018-10049728
A100: VT | B100: FAINI | C100: 10049740 | D100: I/7128 | E100: =VLOOKUP(D:D,Hoja2!A:B,2,FALSE) -> LINEAERRE SA | G100: CC | H100: I/7128 | I100: 21/12/2010 | J100: 363 | K100: 762.3 | L100: 0018 | M100: 0018-10049740
A101: VT | B101: FAINI | C101: 10049741 | D101: I/7128 | E101: =VLOOKUP(D:D,Hoja2!A:B,2,FALSE) -> LINEAERRE SA | G101: CC | H101: I/7128 | I101: 21/12/2010 | J101: 363 | K101: 1125.3 | L101: 0018 | M101: 0018-10049741
A102: VT | B102: FAINI | C102: 10049868 | D102: I/7128 | E102: =VLOOKUP(D:D,Hoja2!A:B,2,FALSE) -> LINEAERRE SA | G102: CC | H102: I/7128 | I102: 10/3/2011 | J102: 726 | K102: 1851.3 | L102: 0018 | M102: 0018-10049868
A103: VT | B103: NCA18 | C103: 57 | D103: I/7128 | E103: =VLOOKUP(D:D,Hoja2!A:B,2,FALSE) -> LINEAERRE SA | G103: CC | H103: I/7128 | I103: 31/5/2022 | J103: -1851.3 | K103: 0 | L103: 0018 | M103: 0018-00000057
A104: VT | B104: FA17 | C104: 6047 | D104: I/7149 | E104: =VLOOKUP(D:D,Hoja2!A:B,2,FALSE) -> COOPERATIVA DE TRABAJO DOÑA FRANCISCA LTDA | F104: SEGU | G104: CC | H104: I/7149 | I104: 15/4/2025 | J104: 7812315 | K104: 7812315 | L104: 0017 | M104: 0017-00006047
A105: VT | B105: FA17 | C105: 6137 | D105: I/7149 | E105: =VLOOKUP(D:D,Hoja2!A:B,2,FALSE) -> COOPERATIVA DE TRABAJO DOÑA FRANCISCA LTDA | F105: SEGU | G105: CC | H105: I/7149 | I105: 13/5/2025 | J105: 8212500 | K105: 16024815 | L105: 0017 | M105: 0017-00006137
A106: VT | B106: NCA17 | C106: 235 | D106: I/7149 | E106: =VLOOKUP(D:D,Hoja2!A:B,2,FALSE) -> COOPERATIVA DE TRABAJO DOÑA FRANCISCA LTDA | F106: SEGU | G106: CC | H106: I/7149 | I106: 16/5/2025 | J106: -7812315 | K106: 8212500 | L106: 0017 | M106: 0017-00000235
A107: VT | B107: NCA17 | C107: 236 | D107: I/7149 | E107: =VLOOKUP(D:D,Hoja2!A:B,2,FALSE) -> COOPERATIVA DE TRABAJO DOÑA FRANCISCA LTDA | F107: SEGU | G107: CC | H107: I/7149 | I107: 16/5/2025 | J107: -8212500 | K107: 0 | L107: 0017 | M107: 0017-00000236
A108: VT | B108: FA17 | C108: 7214 | D108: I/7149 | E108: =VLOOKUP(D:D,Hoja2!A:B,2,FALSE) -> COOPERATIVA DE TRABAJO DOÑA FRANCISCA LTDA | F108: SEGU | G108: CC | H108: I/7149 | I108: 22/4/2026 | J108: 19368800 | K108: 19368800 | L108: 0017 | M108: 0017-00007214
A109: VT | B109: FA17 | C109: 7229 | D109: I/7149 | E109: =VLOOKUP(D:D,Hoja2!A:B,2,FALSE) -> COOPERATIVA DE TRABAJO DOÑA FRANCISCA LTDA | F109: SEGU | G109: CC | H109: I/7149 | I109: 29/4/2026 | J109: 18277600 | K109: 37646400 | L109: 0017 | M109: 0017-00007229
A110: VT | B110: FA17 | C110: 7248 | D110: I/7149 | E110: =VLOOKUP(D:D,Hoja2!A:B,2,FALSE) -> COOPERATIVA DE TRABAJO DOÑA FRANCISCA LTDA | F110: SEGU | G110: CC | H110: I/7149 | I110: 4/5/2026 | J110: 18277600 | K110: 55924000 | L110: 0017 | M110: 0017-00007248
A111: VT | B111: FA17 | C111: 7273 | D111: I/7149 | E111: =VLOOKUP(D:D,Hoja2!A:B,2,FALSE) -> COOPERATIVA DE TRABAJO DOÑA FRANCISCA LTDA | F111: SEGU | G111: CC | H111: I/7149 | I111: 6/5/2026 | J111: 24552000 | K111: 80476000 | L111: 0017 | M111: 0017-00007273
A112: VT | B112: FA17 | C112: 7293 | D112: I/7149 | E112: =VLOOKUP(D:D,Hoja2!A:B,2,FALSE) -> COOPERATIVA DE TRABAJO DOÑA FRANCISCA LTDA | F112: SEGU | G112: CC | H112: I/7149 | I112: 8/5/2026 | J112: 24074600 | K112: 104550600 | L112: 0017 | M112: 0017-00007293
A113: VT | B113: FAINI | C113: 10050061 | D113: I/7151 | E113: =VLOOKUP(D:D,Hoja2!A:B,2,FALSE) -> PESCA ANGELA SA | G113: CC | H113: I/7151 | I113: 1/8/2011 | J113: 1488 | K113: 1488 | L113: 0018 | M113: 0018-10050061
...

Sheet Hoja2
A1: Cuenta | B1: Razón Social
A2: I/860 | B2: PESQUERA EL GRINGO SRL
A3: E/1042 | B3: PACIFIC AMERICAN FISH COMPANY, INC
A4: E/1044 | B4: OCEANPRO FOODS (HONGKONG) CO. LIMITED
A5: E/1045 | B5: OCEANPRO GROUP CO., LIMITED
A6: E/1055 | B6: MORFISH LLC
A7: E/1077 | B7: PRODAKVA LTD.
A8: E/1111 | B8: MICHAEL THOMAS EISSLER FARIAS
A9: E/1114 | B9: GRAND PARTNER AS
A10: E/1125 | B10: ARTI SEAFOOD GMBH
A11: I/7363 | B11: RICH MARINE FISHERY S.A.
A12: I/7364 | B12: PESQUERA BUENAVISTA S.A
... A822: I/7190 | B822: COOP.TRABAJO EL PEHUEN LT
